[{"name":"metadata.json","path":"dist/metadata.json","internal_type":30,"type":"Metadata"},{"name":"vessl","path":"dist/vessl_darwin_arm64/vessl","goos":"darwin","goarch":"arm64","internal_type":4,"type":"Binary","extra":{"Binary":"vessl","Ext":"","ID":"vessl"}},{"name":"vessl","path":"dist/vessl_linux_amd64_v1/vessl","goos":"linux","goarch":"amd64","goamd64":"v1","internal_type":4,"type":"Binary","extra":{"Binary":"vessl","Ext":"","ID":"vessl"}},{"name":"vessl.exe","path":"dist/vessl_windows_amd64_v1/vessl.exe","goos":"windows","goarch":"amd64","goamd64":"v1","internal_type":4,"type":"Binary","extra":{"Binary":"vessl","Ext":".exe","ID":"vessl"}},{"name":"vessl","path":"dist/vessl_darwin_amd64_v1/vessl","goos":"darwin","goarch":"amd64","goamd64":"v1","internal_type":4,"type":"Binary","extra":{"Binary":"vessl","Ext":"","ID":"vessl"}},{"name":"vessl","path":"dist/vessl_linux_arm64/vessl","goos":"linux","goarch":"arm64","internal_type":4,"type":"Binary","extra":{"Binary":"vessl","Ext":"","ID":"vessl"}},{"name":"vessl_Darwin_arm64.tar.gz","path":"dist/vessl_Darwin_arm64.tar.gz","goos":"darwin","goarch":"arm64","internal_type":1,"type":"Archive","extra":{"Binaries":["vessl"],"Checksum":"sha256:8c7c4431d03abf526eaf6bcafabf27fd636d89d16d4adda4c7d9136f8b5958dd","Format":"tar.gz","ID":"default","Replaces":null,"WrappedIn":""}},{"name":"vessl_Linux_arm64.tar.gz","path":"dist/vessl_Linux_arm64.tar.gz","goos":"linux","goarch":"arm64","internal_type":1,"type":"Archive","extra":{"Binaries":["vessl"],"Checksum":"sha256:780a03d21da1455b4540a37a1e38987ef28b62deae8d5477c73b7d8d8a2e994f","Format":"tar.gz","ID":"default","Replaces":null,"WrappedIn":""}},{"name":"vessl_Darwin_x86_64.tar.gz","path":"dist/vessl_Darwin_x86_64.tar.gz","goos":"darwin","goarch":"amd64","goamd64":"v1","internal_type":1,"type":"Archive","extra":{"Binaries":["vessl"],"Checksum":"sha256:6d8c557008645e037e2cd7a30e557263ddc782c6c1afd64a400e2c61cba8f8b1","Format":"tar.gz","ID":"default","Replaces":null,"WrappedIn":""}},{"name":"vessl_Linux_x86_64.tar.gz","path":"dist/vessl_Linux_x86_64.tar.gz","goos":"linux","goarch":"amd64","goamd64":"v1","internal_type":1,"type":"Archive","extra":{"Binaries":["vessl"],"Checksum":"sha256:980f7a2167bec99348549aa71b5e65160dc2cea1046f2f627d113ba5e2032b16","Format":"tar.gz","ID":"default","Replaces":null,"WrappedIn":""}},{"name":"vessl_Windows_x86_64.zip","path":"dist/vessl_Windows_x86_64.zip","goos":"windows","goarch":"amd64","goamd64":"v1","internal_type":1,"type":"Archive","extra":{"Binaries":["vessl.exe"],"Checksum":"sha256:9905fa3621c201dbb9ba926c01197af665bcc2e9327d76c7ec99d3176990aa63","Format":"zip","ID":"default","Replaces":null,"WrappedIn":""}},{"name":"checksums.txt","path":"dist/checksums.txt","internal_type":12,"type":"Checksum","extra":{}},{"name":"vessl.rb","path":"dist/homebrew/vessl.rb","internal_type":16,"type":"Brew Tap","extra":{"BrewConfig":{"name":"vessl","repository":{"owner":"saswatsam786","name":"homebrew-tap","git":{},"pull_request":{"base":{}}},"commit_author":{"name":"Saswat Samal","email":"saswatsam786@gmail.com"},"commit_msg_template":"Brew formula update for {{ .ProjectName }} version {{ .Tag }}","description":"A powerful command-line interface for managing Docker containers","homepage":"https://github.com/saswatsam786/vessl","goarm":"6","goamd64":"v1","tap":{"git":{},"pull_request":{"base":{}}}}}}]